python_sip_client/__init__.py
python_sip_client-0.0.4.dist-info/METADATA
python_sip_client-0.0.4.dist-info/WHEEL
python_sip_client-0.0.4.dist-info/licenses/LICENSE
python_sip_client-0.0.4.dist-info/RECORD
