Metadata-Version: 2.4
Name: python_sip_client
Version: 0.0.4
Summary: A baresip-based, multithreaded, event handling SIP client written in Python
Project-URL: Homepage, https://github.com/mschleid/python_sip_client
Project-URL: Issues, https://github.com/mschleid/python_sip_client/issues
Project-URL: Documentation, https://github.com/mschleid/python_sip_client/wiki
Author-email: Michael Schleider <maschleider@yahoo.com>
License-File: LICENSE
Keywords: baresip,communications,sip,telephony,voip
Classifier: Development Status :: 3 - Alpha
Classifier: License :: OSI Approved :: MIT License
Classifier: Natural Language :: English
Classifier: Programming Language :: Python :: 3
Classifier: Topic :: Communications :: Internet Phone
Requires-Python: >=3.8
Provides-Extra: tests
Requires-Dist: pytest>=6.2.4; extra == 'tests'
